README.txt
gnp.py
setup.py
gnp.egg-info/.DS_Store
gnp.egg-info/PKG-INFO
gnp.egg-info/SOURCES.txt
gnp.egg-info/dependency_links.txt
gnp.egg-info/requires.txt
gnp.egg-info/top_level.txt