Metadata-Version: 1.0
Name: gnp
Version: 0.0.2
Summary: Google News Parser
Home-page: https://github.com/mPAND/gnp
Author: Manuel David Pandian
Author-email: manueldavidpandian@gmail.com
License: UNKNOWN
Platform: UNKNOWN
Classifier: Development Status :: 3 - Alpha
Classifier: License :: OSI Approved :: MIT License
